alerts/__init__.py
alerts/admin.py
alerts/apps.py
alerts/forms.py
alerts/models.py
alerts/tasks.py
alerts/tests.py
alerts/views.py
alerts/migrations/0001_initial.py
alerts/migrations/0002_alter_messagingserviceconfig_project.py
alerts/migrations/0003_messagingserviceconfig_last_failure_error_message_and_more.py
alerts/migrations/0004_alter_messagingserviceconfig_kind.py
alerts/migrations/__init__.py
alerts/service_backends/__init__.py
alerts/service_backends/discord.py
alerts/service_backends/mattermost.py
alerts/service_backends/slack.py
alerts/templates/mails/issue_alert.html
alerts/templates/mails/issue_alert.txt
api/LICENSE
api/README.md
api/event.schema.altered.json
api/event.schema.json
bsmain/__init__.py
bsmain/admin.py
bsmain/apps.py
bsmain/future_python.py
bsmain/models.py
bsmain/tasks.py
bsmain/tests.py
bsmain/urls.py
bsmain/utils.py
bsmain/views.py
bsmain/management/__init__.py
bsmain/management/utils.py
bsmain/management/commands/__init__.py
bsmain/management/commands/check_migrations.py
bsmain/management/commands/convert_mariadb_uuids.py
bsmain/management/commands/create_auth_token.py
bsmain/management/commands/fetch_event_schema_json.py
bsmain/management/commands/makemigrations.py
bsmain/management/commands/migrate.py
bsmain/management/commands/modelcounts.py
bsmain/management/commands/munin.py
bsmain/management/commands/prestart.py
bsmain/management/commands/raise_exception.py
bsmain/management/commands/send_bomb.py
bsmain/management/commands/send_json.py
bsmain/management/commands/showstat.py
bsmain/management/commands/stress_test.py
bsmain/migrations/0001_initial.py
bsmain/migrations/0002_cachedmodelcount.py
bsmain/migrations/__init__.py
bsmain/templates/bsmain/auth_token_list.html
bugsink/__init__.py
bugsink/_version.py
bugsink/api_fields.py
bugsink/api_mixins.py
bugsink/api_pagination.py
bugsink/api_serializers.py
bugsink/app_settings.py
bugsink/authentication.py
bugsink/conf_utils.py
bugsink/context_processors.py
bugsink/dbrouters.py
bugsink-2.0.12.dist-info/licenses/LICENSE
bugsink-2.0.12.dist-info/METADATA
bugsink-2.0.12.dist-info/WHEEL
bugsink-2.0.12.dist-info/entry_points.txt
bugsink-2.0.12.dist-info/top_level.txt
bugsink-2.0.12.dist-info/RECORD
