Metadata-Version: 2.4
Name: bugsink
Version: 2.0.12
Summary: Self-hosted Error Tracking
Author-email: "Bugsink B.V." <info@bugsink.com>
Project-URL: homepage, https://www.bugsink.com/
Project-URL: documentation, https://www.bugsink.com/docs/
Project-URL: issues, https://github.com/bugsink/bugsink/issues
Project-URL: repository, https://github.com/bugsink/bugsink
Classifier: Programming Language :: Python :: 3
Classifier: Programming Language :: Python :: 3.10
Classifier: Programming Language :: Python :: 3.11
Classifier: Programming Language :: Python :: 3.12
Classifier: Programming Language :: Python :: 3.13
Classifier: Programming Language :: Python :: 3.14
Requires-Python: >=3.10
License-File: LICENSE
Requires-Dist: gunicorn==23.0.*
Requires-Dist: Django==5.2.*
Requires-Dist: verbose_csrf_middleware==5.2.*
Requires-Dist: sentry-sdk==2.*
Requires-Dist: django-tailwind==4.2.*
Requires-Dist: jsonschema==4.26.*
Requires-Dist: semver==3.0.*
Requires-Dist: django-admin-autocomplete-filter==0.7.*
Requires-Dist: pygments==2.19.*
Requires-Dist: inotify_simple==2.0.*
Requires-Dist: Brotli==1.2.*
Requires-Dist: python-dateutil==2.9.*
Requires-Dist: whitenoise==6.11.*
Requires-Dist: requests==2.32.*
Requires-Dist: monofy==1.1.*
Requires-Dist: user-agents==2.2.*
Requires-Dist: fastjsonschema==2.21.*
Requires-Dist: ecma426>=0.2.0
Requires-Dist: djangorestframework==3.16.*
Requires-Dist: drf-spectacular[sidecar]
Requires-Dist: symbolic==8.7.2
Dynamic: license-file
